<?xml version="1.0" encoding="utf-8"?>
<aap>
    <tasklist>
        <currenttask domain='diffusion_session' desc='Take mean of images with no diffusion' modality='MRI'>
            
            <qsub>
                <timeBase>0.2</timeBase>
                <memoryBase>0.5</memoryBase>
            </qsub>
            
            <permanenceofoutput>1</permanenceofoutput>
            
            <tol_b0></tol_b0>
            
            <inputstreams>
                <stream>diffusion_data</stream>
                <stream>bvals</stream>
            </inputstreams>
            
            <outputstreams>
                <stream>nodif</stream>
            </outputstreams>
            
        </currenttask>
    </tasklist>
</aap>

